[
 {
  "name": "AL FAROOQUE ORAVAMPURAM",
  "place": "ORAVAMPURAM",
  "zone": "C"
 },
 {
  "name": "AL HASANATH MAMPUZHA",
  "place": "MAMPUZHA",
  "zone": "C"
 },
 {
  "name": "ANVARUL ISLAM THIRURKKAD",
  "place": "THIRURKKAD",
  "zone": "C"
 },
 {
  "name": "ANWARUL HUDA VETTATHUR",
  "place": "VETTATHUR",
  "zone": "C"
 },
 {
  "name": "DARUL ISLAM VALLAPPUZA",
  "place": "VALLAPPUZA",
  "zone": "C"
 },
 {
  "name": "DARUNNAJATH MANNARKKAD",
  "place": "MANNARKKAD",
  "zone": "C"
 },
 {
  "name": "DARUNNAJATH KARUVARAKKUNDU",
  "place": "KARUVARAKKUNDU",
  "zone": "C"
 },
 {
  "name": "IHYA ULOOM PULLISSERY",
  "place": "PULLISSERY",
  "zone": "C"
 },
 {
  "name": "IMAM NAVAVI NATTUKAL",
  "place": "NATTUKAL",
  "zone": "C"
 },
 {
  "name": "IRSHADUL ANAM KOPPAM",
  "place": "KOPPAM",
  "zone": "C"
 },
 {
  "name": "KAMMUSOOFI THEYYOTTUCHIRA",
  "place": "THEYYOTTUCHIRA",
  "zone": "C"
 },
 {
  "name": "MAJMA’ RAHMANIYYA CHERPULASSERY",
  "place": "CHERPULASSERY",
  "zone": "C"
 }
]
